tcms_api/__init__.py
tcms_api/plugin_helpers.py
tcms_api/version.py
tcms_api/xmlrpc.py
tcms_api-15.0.dist-info/licenses/LICENSE
tcms_api-15.0.dist-info/METADATA
tcms_api-15.0.dist-info/WHEEL
tcms_api-15.0.dist-info/top_level.txt
tcms_api-15.0.dist-info/RECORD
